plot_max/__init__.py
plot_max/plot_max.py
plot_max-1.3.4.dist-info/METADATA
plot_max-1.3.4.dist-info/WHEEL
plot_max-1.3.4.dist-info/top_level.txt
plot_max-1.3.4.dist-info/RECORD
