Metadata-Version: 2.1
Name: plot-max
Version: 1.3.4
Summary: high level to use matplotlib
Home-page: http://github.com/pringwong
Author: pring
Author-email: huppid@qq.com
License: None
Platform: UNKNOWN
